gnore/__init__.py
gnore/__main__.py
gnore/config.py
gnore/api/__init__.py
gnore/api/controllers/__init__.py
gnore/api/controllers/base_controller.py
gnore/api/controllers/clean_controller.py
gnore/api/services/__init__.py
gnore/api/services/gnore_service.py
gnore-0.2.2.dist-info/DESCRIPTION.rst
gnore-0.2.2.dist-info/METADATA
gnore-0.2.2.dist-info/RECORD
gnore-0.2.2.dist-info/WHEEL
gnore-0.2.2.dist-info/entry_points.txt
gnore-0.2.2.dist-info/metadata.json
gnore-0.2.2.dist-info/top_level.txt
