Metadata-Version: 2.0
Name: gnore
Version: 0.2.2
Summary: Utility for .gitignore
Home-page: https://github.com/jamrizzi/gnore
Author: Jam Risser
Author-email: jam@jamrizzi.com
License: MIT
Keywords: cli git github clean ignore gitignore command line
Platform: UNKNOWN
Classifier: Development Status :: 4 - Beta
Classifier: Intended Audience :: Developers
Classifier: Topic :: Utilities
Classifier: License :: OSI Approved :: MIT License
Classifier: Programming Language :: Python :: 2
Classifier: Programming Language :: Python :: 2.7
Classifier: Programming Language :: Python :: 3
Classifier: Programming Language :: Python :: 3.3
Classifier: Programming Language :: Python :: 3.4
Classifier: Programming Language :: Python :: 3.5
Requires-Dist: cement (==2.10.2)
